README.md
setup.cfg
setup.py
databiz/__init__.py
databiz/databiz1.py
databiz.egg-info/PKG-INFO
databiz.egg-info/SOURCES.txt
databiz.egg-info/dependency_links.txt
databiz.egg-info/requires.txt
databiz.egg-info/top_level.txt